Asi/ASI.dtd
Asi/ASI2.1.dtd
Asi/ASI2.dtd
Asi/AsiEvaluationException.py
Asi/AsiParsingException.py
Asi/__init__.py
Asi/Definition/CommentAction.py
Asi/Definition/CommentDefinition.py
Asi/Definition/Drug.py
Asi/Definition/DrugClass.py
Asi/Definition/Gene.py
Asi/Definition/LevelAction.py
Asi/Definition/LevelDefinition.py
Asi/Definition/LevelDefinitionComparator.py
Asi/Definition/RangeValue.py
Asi/Definition/Rule.py
Asi/Definition/RuleCondition.py
Asi/Definition/ScoreRangeAction.py
Asi/Definition/__init__.py
Asi/Evaluate/EvaluatedCondition.py
Asi/Evaluate/EvaluatedDrug.py
Asi/Evaluate/EvaluatedDrugClass.py
Asi/Evaluate/EvaluatedGene.py
Asi/Evaluate/__init__.py
Asi/Grammar/AsiGrammarAdapter.py
Asi/Grammar/StringMutationComparator.py
Asi/Grammar/__init__.py
Asi/Grammar/utils.py
Asi/Grammar/Analysis/__init__.py
Asi/Grammar/Lexer/__init__.py
Asi/Grammar/Node/__init__.py
Asi/Grammar/Parser/__init__.py
Asi/XML/XmlAsiTransformer.py
Asi/XML/__init__.py
Asi/data/HIVDB_8.5.d926dfff.xml
Asi/data/updateandsecurity.png
asipython-0.1.0.dist-info/LICENSE
asipython-0.1.0.dist-info/METADATA
asipython-0.1.0.dist-info/WHEEL
asipython-0.1.0.dist-info/top_level.txt
asipython-0.1.0.dist-info/RECORD
