Metadata-Version: 2.1
Name: asipython
Version: 0.1.0
Summary: Python library that calculates viral drug resistance interpretations/scores based on given algorithm and mutation list files
Home-page: https://github.com/phac-nml/asipython.git
Author: Eric Enns
Author-email: eric.enns@canada.ca
License: Apache License, Version 2.0
Platform: any
Classifier: License :: OSI Approved :: Apache Software License
Classifier: Environment :: Console
Classifier: Programming Language :: Python :: 3
